odoo_soup/__init__.py
odoo_soup/compiler.py
odoo_soup/config.py
odoo_soup/converter.py
odoo_soup/default_soups.toml
odoo_soup/main.py
odoo_soup/utils.py
odoo_soup/models/__init__.py
odoo_soup/models/log.py
odoo_soup-1.2.0.dist-info/entry_points.txt
odoo_soup-1.2.0.dist-info/WHEEL
odoo_soup-1.2.0.dist-info/METADATA
odoo_soup-1.2.0.dist-info/RECORD
