Metadata-Version: 2.4
Name: odoo_soup
Version: 1.2.0
Summary: Log tools for Odoo
Author-email: Austin Paskerian <paau@odoo.com>
Requires-Python: >=3.10
Requires-Dist: click>=8.1
Requires-Dist: magicprompt==0.2.5
Requires-Dist: psycopg2-binary==2.9.11
Requires-Dist: sqlalchemy==2.0.43
Requires-Dist: click-spinner==0.1.10
